insardev_pygmtsar/PRM.py
insardev_pygmtsar/PRM_gmtsar.py
insardev_pygmtsar/S1.py
insardev_pygmtsar/S1_align.py
insardev_pygmtsar/S1_base.py
insardev_pygmtsar/S1_dem.py
insardev_pygmtsar/S1_geocode.py
insardev_pygmtsar/S1_gmtsar.py
insardev_pygmtsar/S1_prm.py
insardev_pygmtsar/S1_slc.py
insardev_pygmtsar/S1_tidal.py
insardev_pygmtsar/S1_topo.py
insardev_pygmtsar/S1_transform.py
insardev_pygmtsar/__init__.py
insardev_pygmtsar/data/geoid_egm96_icgem.grd
insardev_pygmtsar/data/google_colab.sh
insardev_pygmtsar-2025.5.4.dev0.dist-info/licenses/LICENSE
insardev_pygmtsar-2025.5.4.dev0.dist-info/METADATA
insardev_pygmtsar-2025.5.4.dev0.dist-info/WHEEL
insardev_pygmtsar-2025.5.4.dev0.dist-info/top_level.txt
insardev_pygmtsar-2025.5.4.dev0.dist-info/RECORD
