Metadata-Version: 2.4
Name: insardev_pygmtsar
Version: 2025.5.4.dev0
Summary: InSAR.dev (Python InSAR): PyGMTSAR backend
Home-page: https://github.com/AlexeyPechnikov/InSARdev
Author: Alexey Pechnikov
Author-email: alexey@pechnikov.dev
License: BSD-3-Clause
Keywords: satellite interferometry,InSAR,remote sensing,Sentinel-1
Classifier: Development Status :: 4 - Beta
Classifier: Intended Audience :: Science/Research
Classifier: Natural Language :: English
Classifier: License :: OSI Approved :: BSD License
Classifier: Operating System :: POSIX
Classifier: Operating System :: POSIX :: Linux
Classifier: Operating System :: MacOS
Classifier: Programming Language :: Python
Classifier: Programming Language :: Python :: 3.10
Classifier: Programming Language :: Python :: 3.11
Requires-Python: >=3.10
License-File: LICENSE
Requires-Dist: insardev_toolkit
Requires-Dist: xarray[complete]
Requires-Dist: numpy
Requires-Dist: pandas>=2.2
Requires-Dist: geopandas
Requires-Dist: distributed>=2024.1.0
Requires-Dist: dask[complete]>=2024.4.1
Requires-Dist: zarr
Requires-Dist: fsspec
Requires-Dist: opencv-python
Requires-Dist: scipy
Requires-Dist: shapely>=2.0.2
Requires-Dist: xmltodict
Requires-Dist: rioxarray
Requires-Dist: statsmodels>=0.14.0
Dynamic: author
Dynamic: author-email
Dynamic: classifier
Dynamic: description
Dynamic: description-content-type
Dynamic: home-page
Dynamic: keywords
Dynamic: license
Dynamic: license-file
Dynamic: requires-dist
Dynamic: requires-python
Dynamic: summary
